jpcorpreg/__init__.py
jpcorpreg/load.py
jpcorpreg/utility.py
jpcorpreg/config/header.json
jpcorpreg-1.7.0.dist-info/licenses/LICENSE
jpcorpreg-1.7.0.dist-info/METADATA
jpcorpreg-1.7.0.dist-info/WHEEL
jpcorpreg-1.7.0.dist-info/top_level.txt
jpcorpreg-1.7.0.dist-info/RECORD
