Metadata-Version: 2.4
Name: jpcorpreg
Version: 1.7.0
Summary: jpcorpreg is a Python library that downloads corporate registry which is published in the Corporate Number Publication Site as a data frame.
Author: new-village
License: Apache-2.0
Project-URL: Homepage, https://github.com/new-village/jpcorpreg
Project-URL: Repository, https://github.com/new-village/jpcorpreg
Requires-Python: >=3.8
License-File: LICENSE
Requires-Dist: requests
Requires-Dist: bs4
Requires-Dist: pandas
Dynamic: license-file
